circdeploy/__init__.py
circdeploy/__main__.py
circdeploy/deploy.py
circdeploy/file_cache.py
circdeploy/files.py
circdeploy-1.0.0.dist-info/METADATA
circdeploy-1.0.0.dist-info/WHEEL
circdeploy-1.0.0.dist-info/entry_points.txt
circdeploy-1.0.0.dist-info/licenses/LICENSE
circdeploy-1.0.0.dist-info/RECORD
