Metadata-Version: 2.4
Name: circdeploy
Version: 1.0.0
Summary: Easily deploy your CircuitPython projects
Project-URL: repository, https://github.com/plasticrake/circdeploy
Project-URL: homepage, https://github.com/plasticrake/circdeploy
Author-email: Patrick Seal <code@plasticrake.com>
License-Expression: MIT
License-File: LICENSE
Keywords: circuitpython
Classifier: Environment :: Console
Classifier: Intended Audience :: Developers
Classifier: Intended Audience :: Education
Classifier: Operating System :: MacOS :: MacOS X
Classifier: Operating System :: Microsoft :: Windows
Classifier: Operating System :: POSIX
Classifier: Topic :: Education
Classifier: Topic :: Software Development :: Build Tools
Classifier: Topic :: Software Development :: Embedded Systems
Classifier: Topic :: System :: Software Distribution
Requires-Python: >=3.10
Requires-Dist: circup<3.0.0,>=2.2.2
Requires-Dist: igittigitt<3.0.0,>=2.1.5
Requires-Dist: platformdirs>=4.3.7
Requires-Dist: rich<15.0.0,>=14.0.0
Requires-Dist: typer<0.16.0,>=0.15.3
